{
  "taskId": "Л-02",
  "taskGoal": "Развить навык 'Локализация' до средний уровень",
  "develops": [
    {
      "skillName": "Локализация",
      "fromLevel": 1,
      "toLevel": 2
    }
  ],
  "subTasks": [
    {
      "title": "Углубленное изучение",
      "description": "Изучить продвинутые аспекты навыка 'Локализация', разобрать сложные случаи"
    },
    {
      "title": "Практическое применение в проекте",
      "description": "Применить навык 'Локализация' в реальном проекте или сложном сценарии"
    },
    {
      "title": "Анализ и оптимизация",
      "description": "Проанализировать эффективность применения навыка и предложить улучшения"
    }
  ],
  "artifacts": [
    {
      "name": "Документация по Локализация",
      "url": "#"
    },
    {
      "name": "Практические примеры Локализация",
      "url": "#"
    }
  ],
  "expectedResult": "Освоение навыка 'Локализация' на средний уровень",
  "estimatedTime": "16 часов"
}