{
  "taskId": "ПК-02",
  "taskGoal": "Развить навык 'Письменная коммуникация' до средний уровень",
  "develops": [
    {
      "skillName": "Письменная коммуникация",
      "fromLevel": 1,
      "toLevel": 2
    }
  ],
  "subTasks": [
    {
      "title": "Углубленное изучение",
      "description": "Изучить продвинутые аспекты навыка 'Письменная коммуникация', разобрать сложные случаи"
    },
    {
      "title": "Практическое применение в проекте",
      "description": "Применить навык 'Письменная коммуникация' в реальном проекте или сложном сценарии"
    },
    {
      "title": "Анализ и оптимизация",
      "description": "Проанализировать эффективность применения навыка и предложить улучшения"
    }
  ],
  "artifacts": [
    {
      "name": "Документация по Письменная коммуникация",
      "url": "#"
    },
    {
      "name": "Практические примеры Письменная коммуникация",
      "url": "#"
    }
  ],
  "expectedResult": "Освоение навыка 'Письменная коммуникация' на средний уровень",
  "estimatedTime": "16 часов"
}