{
  "taskId": "КМ-02",
  "taskGoal": "Улучшить навык мокирования чтобы иметь возможность покрывать большее количество тестов",
  "develops": [
    {
      "skillName": "Клиент-серверные моки",
      "fromLevel": 1,
      "toLevel": 2
    }
  ],
  "subTasks": [
    {
      "title": "Проанализировать смоук/санити фич, которые уже покрыты, на предмет сценариев...",
      "description": "Проанализировать смоук/санити фич, которые уже покрыты, на предмет сценариев связанных с ошибками и выбрать один сценарий. Если таких сценариев нет - выбрать в приложении самый простой."
    },
    {
      "title": "Используя параметры MockVariant покрыть ошибку и проверить что она отображается.",
      "description": "Используя параметры MockVariant покрыть ошибку и проверить что она отображается."
    },
    {
      "title": "Используя freeze/unfreeze функциональность проверить наличие лоадера в одном из...",
      "description": "Используя freeze/unfreeze функциональность проверить наличие лоадера в одном из реализованных сценариев. Учесть что лоадер должен длиться столько, сколько ждем запрос, поэтому проверить что лоадер есть не менее 2 секунд, а потом проверить что контент загрузился корректно после unfreeze."
    }
  ],
  "artifacts": [
    {
      "name": "Практические примеры Клиент-серверные моки",
      "url": "#"
    }
  ],
  "expectedResult": "Работающий тест с моком ошибки и лоадера",
  "estimatedTime": "40 часов"
}