{
  "taskId": "МЛ-02",
  "taskGoal": "Развить навык 'Мотивация людей' до средний уровень",
  "develops": [
    {
      "skillName": "Мотивация людей",
      "fromLevel": 1,
      "toLevel": 2
    }
  ],
  "subTasks": [
    {
      "title": "Углубленное изучение",
      "description": "Изучить продвинутые аспекты навыка 'Мотивация людей', разобрать сложные случаи"
    },
    {
      "title": "Практическое применение в проекте",
      "description": "Применить навык 'Мотивация людей' в реальном проекте или сложном сценарии"
    },
    {
      "title": "Анализ и оптимизация",
      "description": "Проанализировать эффективность применения навыка и предложить улучшения"
    }
  ],
  "artifacts": [
    {
      "name": "Документация по Мотивация людей",
      "url": "#"
    },
    {
      "name": "Практические примеры Мотивация людей",
      "url": "#"
    }
  ],
  "expectedResult": "Освоение навыка 'Мотивация людей' на средний уровень",
  "estimatedTime": "16 часов"
}