{
  "taskId": "ПЛВ-01",
  "taskGoal": "Развить навык 'Проведение личных встреч и 1-1' до базовый уровень",
  "develops": [
    {
      "skillName": "Проведение личных встреч и 1-1",
      "fromLevel": 0,
      "toLevel": 1
    }
  ],
  "subTasks": [
    {
      "title": "Изучение теории: Проведение личных встреч и 1-1",
      "description": "Изучить теоретические основы навыка 'Проведение личных встреч и 1-1', понять основные концепции и принципы"
    },
    {
      "title": "Практическое применение",
      "description": "Применить полученные знания на практике в простых сценариях"
    },
    {
      "title": "Создание чек-листа",
      "description": "Составить чек-лист основных моментов для навыка 'Проведение личных встреч и 1-1'"
    }
  ],
  "artifacts": [
    {
      "name": "Документация по Проведение личных встреч и 1-1",
      "url": "#"
    },
    {
      "name": "Практические примеры Проведение личных встреч и 1-1",
      "url": "#"
    }
  ],
  "expectedResult": "Освоение навыка 'Проведение личных встреч и 1-1' на базовый уровень",
  "estimatedTime": "8 часов"
}